slurmui/__init__.py
slurmui/_version.py
slurmui/debug_strings.py
slurmui/slurmui.py
slurmui/slurmui_cli.py
slurmui-0.3.0.4.dist-info/METADATA
slurmui-0.3.0.4.dist-info/WHEEL
slurmui-0.3.0.4.dist-info/entry_points.txt
slurmui-0.3.0.4.dist-info/top_level.txt
slurmui-0.3.0.4.dist-info/RECORD
