Metadata-Version: 2.1
Name: slurmui
Version: 0.3.0.4
Summary: Terminal UI for Slurm
Home-page: https://github.com/SirWyver/slurmui
Author: Norman Müller
Author-email: norman.mueller@tum.de
Classifier: Programming Language :: Python :: 3
Classifier: License :: OSI Approved :: MIT License
Classifier: Operating System :: OS Independent
Requires-Python: >=3.6
Requires-Dist: textual
Requires-Dist: pandas
